pyretrodesign/__init__.py
pyretrodesign/pyretrodesign.py
pyretrodesign/test/__init__.py
pyretrodesign/test/test_pyretrodesign.py
pyretrodesign-0.0.1.dist-info/LICENSE
pyretrodesign-0.0.1.dist-info/METADATA
pyretrodesign-0.0.1.dist-info/WHEEL
pyretrodesign-0.0.1.dist-info/top_level.txt
pyretrodesign-0.0.1.dist-info/RECORD
